Metadata-Version: 2.1
Name: zkappumstad
Version: 0.2.0
Summary: CLI AI Agent for zkApps Developers
Home-page: https://github.com/UmstadAI/zkAppUmstad/tree/main/cli
Author: Berkin Gurcan, Dogukan Akar
Author-email: berkingurcan@gmail.com, dogukanakarc@gmail.com
Keywords: zkapps,zkappumstad,zkapps agent
Classifier: Topic :: Software Development :: Build Tools
Classifier: License :: OSI Approved :: MIT License
Classifier: Programming Language :: Python :: 3
Classifier: Programming Language :: Python :: 3.10
Requires-Python: >=3.10
Requires-Dist: annotated-types ==0.6.0
Requires-Dist: anyio ==3.7.1
Requires-Dist: black ==23.12.1
Requires-Dist: certifi ==2023.11.17
Requires-Dist: charset-normalizer ==3.3.2
Requires-Dist: click ==8.1.7
Requires-Dist: colorama ==0.4.6
Requires-Dist: distro ==1.8.0
Requires-Dist: dnspython ==2.4.2
Requires-Dist: exceptiongroup ==1.2.0
Requires-Dist: h11 ==0.14.0
Requires-Dist: httpcore ==1.0.2
Requires-Dist: httpx ==0.25.2
Requires-Dist: idna ==3.6
Requires-Dist: loguru ==0.7.2
Requires-Dist: markdown-it-py ==3.0.0
Requires-Dist: mdurl ==0.1.2
Requires-Dist: mypy-extensions ==1.0.0
Requires-Dist: numpy ==1.26.2
Requires-Dist: openai ==1.3.7
Requires-Dist: packaging ==23.2
Requires-Dist: pathspec ==0.12.1
Requires-Dist: pinecone-client ==2.2.4
Requires-Dist: platformdirs ==4.1.0
Requires-Dist: pydantic ==2.5.2
Requires-Dist: pydantic-core ==2.14.5
Requires-Dist: Pygments ==2.17.2
Requires-Dist: python-dateutil ==2.8.2
Requires-Dist: python-dotenv ==1.0.0
Requires-Dist: PyYAML ==6.0.1
Requires-Dist: requests ==2.31.0
Requires-Dist: rich ==13.7.0
Requires-Dist: six ==1.16.0
Requires-Dist: sniffio ==1.3.0
Requires-Dist: tomli ==2.0.1
Requires-Dist: tqdm ==4.66.1
Requires-Dist: typing-extensions ==4.8.0
Requires-Dist: urllib3 ==2.1.0
